modules/spi/source/spi_master.v
module spi_master #(
	parameter p_prescaler = 25, /* spi clock prescaler */
	parameter p_cpol = 0,	/* clock polarity */
	parameter p_max_data_buffer = 64, /* Max data buffer in bits */
	parameter pw_data_index = 6 /* Width for data index */
)(
	input clk,
	input rst,

	input [p_max_data_buffer-1:0] ip_data, /* parallel data to send */
	input [pw_data_index-1:0] ip_data_count, /* number of bits to send */
	input i_data_valid, /* input data ready to send */
	
	output reg [ p_max_data_buffer-1:0] orp_data, /* parallel data readed */
	output o_data_ready, /* SPI module ready to receive data */

	output reg or_mosi, /* master output, slave input pin */
	input i_miso, /* master input, slave output pin */
	output o_sck /* spi clock pin */
	);

	localparam pw_prescaler = $clog2(p_prescaler); /* Prescaler width */

	localparam st_idle = 3'd0;
	localparam st_data_w = 3'd1;
	localparam st_data_r = 3'd2;

	reg [pw_data_index-1:0] rp_data_index; /* data index */
	reg [p_max_data_buffer-1:0] rp_data_in_hold; /* data to send registered */
	reg [p_max_data_buffer-1:0] rp_data_out_hold; /* data received registered */
	reg [2:0] r3_state; /* spi fsm state */
	reg [pw_prescaler-1:0] rp_half_period_counter; /* half period counter */
	reg [pw_data_index:0] rp_data_count; /* Data count registered */
	reg r_sck; /* spi clock temp */

	assign o_sck = (!p_cpol)? r_sck: ~r_sck;

	assign o_data_ready = ((r3_state == st_idle) && (i_data_valid == 1'b0))? 1'b1: 1'b0;

	always @( posedge clk)
		if(rst) begin
			or_mosi <= 1'b0;
			r_sck <= 1'b0;
			r3_state <= st_idle;
			rp_data_out_hold <= 0;
			rp_data_in_hold <= 0;
			rp_data_count = 0;
		end
		else
			case (r3_state)
				st_idle: begin
					if (i_data_valid) r3_state <= st_data_w;
					else r3_state <= st_idle;

					or_mosi <= 1'b0;
					r_sck <= 1'b0;
					rp_data_out_hold <= ip_data;
					rp_data_index <= 0;
					orp_data <= rp_data_in_hold;
					rp_data_count <= ip_data_count-1;
          rp_half_period_counter <= 0;
				end
				st_data_w: begin
					or_mosi <= rp_data_out_hold[ip_data_count-rp_data_index-1];
					r_sck <= 1'b0;

          if(rp_half_period_counter <= (p_prescaler >> 1)) begin 
            rp_half_period_counter <= rp_half_period_counter + 1;
            r3_state <= st_data_w;
          end
          else begin
            rp_half_period_counter <= 0;
            r3_state <= st_data_r;
          end
				end
				st_data_r: begin
					rp_data_in_hold[ip_data_count-rp_data_index-1] <= i_miso;
					r_sck <= 1'b1;

					rp_data_index <= (rp_half_period_counter == 0) ? rp_data_index + 1 : rp_data_index;

          if(rp_half_period_counter <= (p_prescaler >> 1)) begin 
            rp_half_period_counter <= rp_half_period_counter + 1;
            r3_state <= st_data_r;
          end
          else begin
            rp_half_period_counter <= 0;
            r3_state <= (rp_data_index > rp_data_count) ? st_idle : st_data_w;
          end
				end
			endcase

endmodule

modules/spi/source/spi_slave.v
module spi_slave #(
  parameter p_data_buffer_length = 32, /* input data buffer length */
  parameter p_width_buffer_length = $clog2(p_data_buffer_length)+1, /* input data buffer width */
  parameter p_cpol = 0 /* clock polarity */
)(
  input clk,
  input rst,

  input [p_data_buffer_length-1:0] ip_data_out, /* data to send */
  input [p_width_buffer_length-1:0] ip_data_count, /* data bit count */

  output reg [p_data_buffer_length-1:0] op_data_in, /* data received */
  output o_data_valid, /* new transaction finished */

  output o_busy, /* spi interface is busy */
  
  input i_sclk, /* spi sclk input */
  input i_mosi, /* spi mosi input */
  output reg or_miso /* spi miso output */
);

  localparam lp_index_width = $clog2(p_data_buffer_length)+1; /* index width */

  wire [1:0] w2_sck_end_edge; /* detect idle sck state (CPOL = 0 or CPOL = 1) */
  wire [1:0] w2_read_edge; /* reading edge */
  wire [1:0] w2_write_edge; /* writing edge */

  reg [1:0] r2_spi_state; /* state for spi transaction */
  reg [p_data_buffer_length-1:0] rp_data_out; /* registered data received */
  reg [1:0] r2_clock_edge_detector; /* clock edge detector */
  reg [lp_index_width-1:0] rp_data_index; /* data index */

  assign w2_sck_end_edge = (p_cpol) ? 2'b01 : 2'b10;
  assign w2_read_edge = (p_cpol) ? 2'b10 : 2'b01;
  assign w2_write_edge = (p_cpol) ? 2'b01 : 2'b10;

  always @(posedge clk)
    if (rst)
      r2_clock_edge_detector <= 2'b00;
    else
      r2_clock_edge_detector <= {r2_clock_edge_detector[0], i_sclk};

  always @(posedge clk)
    if (rst) begin
      r2_spi_state <= 2'd0;
      rp_data_out <= {p_data_buffer_length{1'b0}};
      op_data_in <= {p_data_buffer_length{1'b0}};
      rp_data_index <= ip_data_count - 1;
      or_miso <= 1'b0;
    end
    else
    begin
      case(r2_spi_state)
      2'b00: begin
        r2_spi_state <= (^r2_clock_edge_detector)? 2'b01: 2'b00;

        rp_data_out <= ip_data_out;
        or_miso <= rp_data_out[p_data_buffer_length-1];

        rp_data_index <= rp_data_index;
        op_data_in[rp_data_index] <= (r2_clock_edge_detector == w2_read_edge)? i_mosi: op_data_in[rp_data_index]; 
      end

      2'b01: begin
        r2_spi_state <= (((rp_data_index == 0) && (r2_clock_edge_detector == w2_sck_end_edge)))? 2'b10: 2'b01;
        
        rp_data_index <= (r2_clock_edge_detector == w2_write_edge)? rp_data_index - 1: rp_data_index;
        op_data_in[rp_data_index] <= (r2_clock_edge_detector == w2_read_edge)? i_mosi: op_data_in[rp_data_index];
        
        or_miso <= rp_data_out[rp_data_index];
      end

      2'b10: begin
        
        rp_data_index <= ip_data_count - 1; 
        r2_spi_state <= 2'b00;

      end
      endcase

    end

  assign o_data_valid = (r2_spi_state == 2'b10)? 1'b1: 1'b0;
  assign o_busy = r2_spi_state[0];

endmodule

modules/spi/test/spi_tb.v
/**** Global timescale ****/
`timescale 10ns/10ns
`define clkcycle 4

/**** Global definitions ****/
`define _1us 100
`define _10us 1000
`define _100us 10000
`define _1ms 100000
`define _10ms 1000000
`define _100ms 10000000
`define _100ns 10
`define _40ns 4
`define _30ns 3

`define max_test_cases 4

module spi_tb();

  /**** Fixed test signals ****/
  integer fd;
  integer error_counter = 0;
  integer test_count = 0;
  integer i;
  integer flag = 0;
  integer verbose = 0;

  /**** Test signals ****/
  reg clk25;
  reg resetn;

  wire w_miso;
  wire w_mosi;
  wire w_sck;

  reg [23:0] r24_data_to_send_master; /* data that master is sendind */
  wire [23:0] w24_data_received_master; /* data that master is receiving */
  reg r_send_data; /* send data */
  wire w_master_ready; /* master ready */

  reg [23:0] r24_data_to_send_slave; /* data that slave is sendind */
  wire [23:0] w24_data_received_slave; /* data that slave is receiving */
  wire w_received_slave; /* new data received in slave */

  /**** Clock generation ****/
  initial begin
    clk25 = 1'b0;
    #(`clkcycle/2);
    forever
    #(`clkcycle/2) clk25 = ~clk25;
  end

  /**** Test modules instantiation ****/
  spi_slave #(
  .p_data_buffer_length(24), /* input data buffer length */
  .p_cpol(0) /* clock polarity */
  ) spi_slave (
  .clk(clk25),
  .rst(!resetn),
  .ip_data_out(r24_data_to_send_slave), /* data to send */
  .ip_data_count(5'd24), /* data bit count */
  .op_data_in(w24_data_received_slave), /* data received */
  .o_data_valid(w_received_slave), /* new transaction finished */
  .o_busy(), /* spi interface is busy */
  .i_sclk(w_sck), /* spi sclk input */
  .i_mosi(w_mosi), /* spi mosi input */
  .or_miso(w_miso) /* spi miso output */
  );

  spi_master #(
	.p_prescaler(8), /* spi clock prescaler */
	.p_cpol(0),	/* clock polarity */
	.p_max_data_buffer(32), /* Max data buffer in bits */
	.pw_data_index(5) /* Width for data index */
  ) spi_master (
  .clk(clk25),
  .rst(!resetn),
	.ip_data(r24_data_to_send_master), /* parallel data to send */
	.ip_data_count(5'd24), /* number of bits to send */
	.i_data_valid(r_send_data), /* input data ready to send */
	.orp_data(w24_data_received_master), /* parallel data readed */
	.o_data_ready(w_master_ready), /* SPI module ready to receive data */
	.or_mosi(w_mosi), /* master output, slave input pin */
	.i_miso(w_miso), /* master input, slave output pin */
	.o_sck(w_sck) /* spi clock pin */
	);


  /**** Test flow ****/
  initial begin

    $dumpfile ("spi_tb.vcd"); // Change filename as appropriate. 
    $dumpvars();

    $display("[INFO] >> Setting initial conditions.");
    
    /*** Reset management ***/
    reset_task();

    /*** Init test flow ***/
    $display("[INFO] >> Test init");
    r24_data_to_send_master <= 24'd0;
    r_send_data <= 1'b0;
    r24_data_to_send_slave <= 24'd0;
    
    /*** Test cases ***/
    repeat(10) begin
      packet_send();
      #(`_1us);
    end

    #(`_1us);
    $finish();

  end

  task packet_send;
  begin

    $display("Packet send");

    r24_data_to_send_master <= $urandom();
    r24_data_to_send_slave <= $urandom();

    r_send_data <= 1'b1;
    #(`clkcycle);
    r_send_data <= 1'b0;

    fork
      begin: f_transaction
        @(posedge w_received_slave);
        
        if(w_master_ready) $display("Master complete sending");
        else $error("Master not complete sending");
        
        disable f_timeout;
      end
      begin: f_timeout
        #(2*`_10us);
        
        if(w_master_ready) $error("Slave not complete reception");
        else $error("Master not complete sending");
        
        disable f_transaction;
      end
    join

    if(w24_data_received_slave != r24_data_to_send_master) begin
      $error("Received data from slave is different from master sending");
      $display("Slave %h, Master %h", w24_data_received_slave, r24_data_to_send_master);
    end
    if(w24_data_received_master != r24_data_to_send_slave) begin
      $error("Received data from master is different from slave sending");
      $display("Slave %h, Master %h", r24_data_to_send_slave, w24_data_received_master);
    end

  end
  endtask


  task reset_task;
  begin
    $info("Resetting module.");
    resetn <= 0;

    $info("Release Reset");
    #(20*`clkcycle);
    resetn <= 1;

  end
  endtask

endmodule

modules/spi/test/spi_tb.vcd
$date
	Mon May 26 16:14:16 2025
$end
$version
	Icarus Verilog
$end
$timescale
	10ns
$end
$scope module spi_tb $end
$var wire 1 ! w_sck $end
$var wire 1 " w_received_slave $end
$var wire 1 # w_mosi $end
$var wire 1 $ w_miso $end
$var wire 1 % w_master_ready $end
$var wire 24 & w24_data_received_slave [23:0] $end
$var wire 24 ' w24_data_received_master [23:0] $end
$var reg 1 ( clk25 $end
$var reg 24 ) r24_data_to_send_master [23:0] $end
$var reg 24 * r24_data_to_send_slave [23:0] $end
$var reg 1 + r_send_data $end
$var reg 1 , resetn $end
$var integer 32 - error_counter [31:0] $end
$var integer 32 . flag [31:0] $end
$var integer 32 / test_count [31:0] $end
$var integer 32 0 verbose [31:0] $end
$scope module spi_master $end
$var wire 1 ( clk $end
$var wire 1 + i_data_valid $end
$var wire 32 1 ip_data [31:0] $end
$var wire 5 2 ip_data_count [4:0] $end
$var wire 1 ! o_sck $end
$var wire 1 3 rst $end
$var wire 1 % o_data_ready $end
$var wire 1 $ i_miso $end
$var parameter 32 4 p_cpol $end
$var parameter 32 5 p_max_data_buffer $end
$var parameter 32 6 p_prescaler $end
$var parameter 32 7 pw_data_index $end
$var parameter 32 8 pw_prescaler $end
$var parameter 3 9 st_data_r $end
$var parameter 3 : st_data_w $end
$var parameter 3 ; st_idle $end
$var reg 1 # or_mosi $end
$var reg 32 < orp_data [31:0] $end
$var reg 3 = r3_state [2:0] $end
$var reg 1 > r_sck $end
$var reg 6 ? rp_data_count [5:0] $end
$var reg 32 @ rp_data_in_hold [31:0] $end
$var reg 5 A rp_data_index [4:0] $end
$var reg 32 B rp_data_out_hold [31:0] $end
$var reg 3 C rp_half_period_counter [2:0] $end
$upscope $end
$scope module spi_slave $end
$var wire 1 ( clk $end
$var wire 1 # i_mosi $end
$var wire 1 ! i_sclk $end
$var wire 6 D ip_data_count [5:0] $end
$var wire 24 E ip_data_out [23:0] $end
$var wire 1 F rst $end
$var wire 2 G w2_read_edge [1:0] $end
$var wire 2 H w2_sck_end_edge [1:0] $end
$var wire 2 I w2_write_edge [1:0] $end
$var wire 1 " o_data_valid $end
$var wire 1 J o_busy $end
$var parameter 33 K lp_index_width $end
$var parameter 32 L p_cpol $end
$var parameter 32 M p_data_buffer_length $end
$var parameter 33 N p_width_buffer_length $end
$var reg 24 O op_data_in [23:0] $end
$var reg 1 $ or_miso $end
$var reg 2 P r2_clock_edge_detector [1:0] $end
$var reg 2 Q r2_spi_state [1:0] $end
$var reg 6 R rp_data_index [5:0] $end
$var reg 24 S rp_data_out [23:0] $end
$upscope $end
$scope task packet_send $end
$scope begin f_timeout $end
$upscope $end
$scope begin f_transaction $end
$upscope $end
$upscope $end
$scope task reset_task $end
$upscope $end
$upscope $end
$enddefinitions $end
$comment Show the parameter values. $end
$dumpall
b110 N
b11000 M
b0 L
b110 K
b0 ;
b1 :
b10 9
b11 8
b101 7
b1000 6
b100000 5
b0 4
$end
#0
$dumpvars
bx S
bx R
bx Q
bx P
bx O
xJ
b10 I
b10 H
b1 G
1F
bx E
b11000 D
bx C
bx B
bx A
bx @
bx ?
x>
bx =
bx <
13
b11000 2
b0xxxxxxxxxxxxxxxxxxxxxxxx 1
b0 0
b0 /
b0 .
b0 -
0,
x+
bx *
bx )
0(
bx '
bx &
x%
x$
x#
x"
x!
$end
#4
0"
0J
b0 P
0$
b10111 R
b0 &
b0 O
b0 S
b0 Q
b0 @
b0 B
b0 =
0!
0>
0#
b0 ?
1(
#6
0(
#8
1(
#10
0(
#12
1(
#14
0(
#16
1(
#18
0(
#20
1(
#22
0(
#24
1(
#26
0(
#28
1(
#30
0(
#32
1(
#34
0(
#36
1(
#38
0(
#40
1(
#42
0(
#44
1(
#46
0(
#48
1(
#50
0(
#52
1(
#54
0(
#56
1(
#58
0(
#60
1(
#62
0(
#64
1(
#66
0(
#68
1(
#70
0(
#72
1(
#74
0(
#76
1(
#78
0(
#80
0%
b100010010101111010000001 *
b100010010101111010000001 E
1+
b101010011010100100100 1
b101010011010100100100 )
0F
03
1,
1(
#82
0(
#84
b0 '
b100010010101111010000001 S
b0 C
b10111 ?
b0 <
b0 A
b101010011010100100100 B
b1 =
0+
1(
#86
0(
#88
b1 C
1$
1(
#90
0(
#92
b10 C
1(
#94
0(
#96
b11 C
1(
#98
0(
#100
b100 C
1(
#102
0(
#104
b101 C
1(
#106
0(
#108
b10 =
b0 C
1(
#110
0(
#112
b1 C
b1 A
1!
1>
b100000000000000000000000 @
1(
#114
0(
#116
b1 P
b10 C
b110000000000000000000000 @
1(
#118
0(
#120
1J
b11 C
b1 Q
b11 P
1(
#122
0(
#124
b100 C
1(
#126
0(
#128
b101 C
1(
#130
0(
#132
b1 =
b0 C
1(
#134
0(
#136
b1 C
0!
0>
1(
#138
0(
#140
b10 P
b10 C
1(
#142
0(
#144
b11 C
b10110 R
b0 P
1(
#146
0(
#148
0$
b100 C
1(
#150
0(
#152
b101 C
1(
#154
0(
#156
b10 =
b0 C
1(
#158
0(
#160
b1 C
b10 A
1!
1>
b100000000000000000000000 @
1(
#162
0(
#164
b1 P
b10 C
1(
#166
0(
#168
b11 C
b11 P
1(
#170
0(
#172
b100 C
1(
#174
0(
#176
b101 C
1(
#178
0(
#180
b1 =
b0 C
1(
#182
0(
#184
b1 C
0!
0>
1(
#186
0(
#188
b10 P
b10 C
1(
#190
0(
#192
b11 C
b10101 R
b0 P
1(
#194
0(
#196
b100 C
1(
#198
0(
#200
b101 C
1(
#202
0(
#204
b10 =
b0 C
1(
#206
0(
#208
b1 C
b11 A
1!
1>
1(
#210
0(
#212
b1 P
b10 C
1(
#214
0(
#216
b11 C
b11 P
1(
#218
0(
#220
b100 C
1(
#222
0(
#224
b101 C
1(
#226
0(
#228
b1 =
b0 C
1(
#230
0(
#232
b1 C
0!
0>
1#
1(
#234
0(
#236
b10 P
b10 C
1(
#238
0(
#240
b11 C
b10100 R
b0 P
1(
#242
0(
#244
b100 C
1(
#246
0(
#248
b101 C
1(
#250
0(
#252
b10 =
b0 C
1(
#254
0(
#256
b1 C
b100 A
1!
1>
1(
#258
0(
#260
b1 P
b10 C
1(
#262
0(
#264
b11 C
b100000000000000000000 &
b100000000000000000000 O
b11 P
1(
#266
0(
#268
b100 C
1(
#270
0(
#272
b101 C
1(
#274
0(
#276
b1 =
b0 C
1(
#278
0(
#280
b1 C
0!
0>
0#
1(
#282
0(
#284
b10 P
b10 C
1(
#286
0(
#288
b11 C
b10011 R
b0 P
1(
#290
0(
#292
1$
b100 C
1(
#294
0(
#296
b101 C
1(
#298
0(
#300
b10 =
b0 C
1(
#302
0(
#304
b1 C
b101 A
1!
1>
b100010000000000000000000 @
1(
#306
0(
#308
b1 P
b10 C
b100011000000000000000000 @
1(
#310
0(
#312
b11 C
b11 P
1(
#314
0(
#316
b100 C
1(
#318
0(
#320
b101 C
1(
#322
0(
#324
b1 =
b0 C
1(
#326
0(
#328
b1 C
0!
0>
1#
1(
#330
0(
#332
b10 P
b10 C
1(
#334
0(
#336
b11 C
b10010 R
b0 P
1(
#338
0(
#340
0$
b100 C
1(
#342
0(
#344
b101 C
1(
#346
0(
#348
b10 =
b0 C
1(
#350
0(
#352
b1 C
b110 A
1!
1>
b100010000000000000000000 @
1(
#354
0(
#356
b1 P
b10 C
1(
#358
0(
#360
b11 C
b101000000000000000000 &
b101000000000000000000 O
b11 P
1(
#362
0(
#364
b100 C
1(
#366
0(
#368
b101 C
1(
#370
0(
#372
b1 =
b0 C
1(
#374
0(
#376
b1 C
0!
0>
0#
1(
#378
0(
#380
b10 P
b10 C
1(
#382
0(
#384
b11 C
b10001 R
b0 P
1(
#386
0(
#388
b100 C
1(
#390
0(
#392
b101 C
1(
#394
0(
#396
b10 =
b0 C
1(
#398
0(
#400
b1 C
b111 A
1!
1>
1(
#402
0(
#404
b1 P
b10 C
1(
#406
0(
#408
b11 C
b11 P
1(
#410
0(
#412
b100 C
1(
#414
0(
#416
b101 C
1(
#418
0(
#420
b1 =
b0 C
1(
#422
0(
#424
b1 C
0!
0>
1#
1(
#426
0(
#428
b10 P
b10 C
1(
#430
0(
#432
b11 C
b10000 R
b0 P
1(
#434
0(
#436
1$
b100 C
1(
#438
0(
#440
b101 C
1(
#442
0(
#444
b10 =
b0 C
1(
#446
0(
#448
b1 C
b1000 A
1!
1>
b100010010000000000000000 @
1(
#450
0(
#452
b1 P
b10 C
b100010011000000000000000 @
1(
#454
0(
#456
b11 C
b101010000000000000000 &
b101010000000000000000 O
b11 P
1(
#458
0(
#460
b100 C
1(
#462
0(
#464
b101 C
1(
#466
0(
#468
b1 =
b0 C
1(
#470
0(
#472
b1 C
0!
0>
0#
1(
#474
0(
#476
b10 P
b10 C
1(
#478
0(
#480
b11 C
b1111 R
b0 P
1(
#482
0(
#484
0$
b100 C
1(
#486
0(
#488
b101 C
1(
#490
0(
#492
b10 =
b0 C
1(
#494
0(
#496
b1 C
b1001 A
1!
1>
b100010010000000000000000 @
1(
#498
0(
#500
b1 P
b10 C
1(
#502
0(
#504
b11 C
b11 P
1(
#506
0(
#508
b100 C
1(
#510
0(
#512
b101 C
1(
#514
0(
#516
b1 =
b0 C
1(
#518
0(
#520
b1 C
0!
0>
1(
#522
0(
#524
b10 P
b10 C
1(
#526
0(
#528
b11 C
b1110 R
b0 P
1(
#530
0(
#532
1$
b100 C
1(
#534
0(
#536
b101 C
1(
#538
0(
#540
b10 =
b0 C
1(
#542
0(
#544
b1 C
b1010 A
1!
1>
b100010010100000000000000 @
1(
#546
0(
#548
b1 P
b10 C
b100010010110000000000000 @
1(
#550
0(
#552
b11 C
b11 P
1(
#554
0(
#556
b100 C
1(
#558
0(
#560
b101 C
1(
#562
0(
#564
b1 =
b0 C
1(
#566
0(
#568
b1 C
0!
0>
1#
1(
#570
0(
#572
b10 P
b10 C
1(
#574
0(
#576
b11 C
b1101 R
b0 P
1(
#578
0(
#580
0$
b100 C
1(
#582
0(
#584
b101 C
1(
#586
0(
#588
b10 =
b0 C
1(
#590
0(
#592
b1 C
b1011 A
1!
1>
b100010010100000000000000 @
1(
#594
0(
#596
b1 P
b10 C
1(
#598
0(
#600
b11 C
b101010010000000000000 &
b101010010000000000000 O
b11 P
1(
#602
0(
#604
b100 C
1(
#606
0(
#608
b101 C
1(
#610
0(
#612
b1 =
b0 C
1(
#614
0(
#616
b1 C
0!
0>
1(
#618
0(
#620
b10 P
b10 C
1(
#622
0(
#624
b11 C
b1100 R
b0 P
1(
#626
0(
#628
1$
b100 C
1(
#630
0(
#632
b101 C
1(
#634
0(
#636
b10 =
b0 C
1(
#638
0(
#640
b1 C
b1100 A
1!
1>
b100010010101000000000000 @
1(
#642
0(
#644
b1 P
b10 C
b100010010101100000000000 @
1(
#646
0(
#648
b11 C
b101010011000000000000 &
b101010011000000000000 O
b11 P
1(
#650
0(
#652
b100 C
1(
#654
0(
#656
b101 C
1(
#658
0(
#660
b1 =
b0 C
1(
#662
0(
#664
b1 C
0!
0>
0#
1(
#666
0(
#668
b10 P
b10 C
1(
#670
0(
#672
b11 C
b1011 R
b0 P
1(
#674
0(
#676
b100 C
1(
#678
0(
#680
b101 C
1(
#682
0(
#684
b10 =
b0 C
1(
#686
0(
#688
b1 C
b1101 A
1!
1>
1(
#690
0(
#692
b1 P
b10 C
b100010010101110000000000 @
1(
#694
0(
#696
b11 C
b11 P
1(
#698
0(
#700
b100 C
1(
#702
0(
#704
b101 C
1(
#706
0(
#708
b1 =
b0 C
1(
#710
0(
#712
b1 C
0!
0>
1#
1(
#714
0(
#716
b10 P
b10 C
1(
#718
0(
#720
b11 C
b1010 R
b0 P
1(
#722
0(
#724
b100 C
1(
#726
0(
#728
b101 C
1(
#730
0(
#732
b10 =
b0 C
1(
#734
0(
#736
b1 C
b1110 A
1!
1>
1(
#738
0(
#740
b1 P
b10 C
b100010010101111000000000 @
1(
#742
0(
#744
b11 C
b101010011010000000000 &
b101010011010000000000 O
b11 P
1(
#746
0(
#748
b100 C
1(
#750
0(
#752
b101 C
1(
#754
0(
#756
b1 =
b0 C
1(
#758
0(
#760
b1 C
0!
0>
0#
1(
#762
0(
#764
b10 P
b10 C
1(
#766
0(
#768
b11 C
b1001 R
b0 P
1(
#770
0(
#772
b100 C
1(
#774
0(
#776
b101 C
1(
#778
0(
#780
b10 =
b0 C
1(
#782
0(
#784
b1 C
b1111 A
1!
1>
1(
#786
0(
#788
b1 P
b10 C
b100010010101111100000000 @
1(
#790
0(
#792
b11 C
b11 P
1(
#794
0(
#796
b100 C
1(
#798
0(
#800
b101 C
1(
#802
0(
#804
b1 =
b0 C
1(
#806
0(
#808
b1 C
0!
0>
1#
1(
#810
0(
#812
b10 P
b10 C
1(
#814
0(
#816
b11 C
b1000 R
b0 P
1(
#818
0(
#820
0$
b100 C
1(
#822
0(
#824
b101 C
1(
#826
0(
#828
b10 =
b0 C
1(
#830
0(
#832
b1 C
b10000 A
1!
1>
b100010010101111000000000 @
1(
#834
0(
#836
b1 P
b10 C
1(
#838
0(
#840
b11 C
b101010011010100000000 &
b101010011010100000000 O
b11 P
1(
#842
0(
#844
b100 C
1(
#846
0(
#848
b101 C
1(
#850
0(
#852
b1 =
b0 C
1(
#854
0(
#856
b1 C
0!
0>
0#
1(
#858
0(
#860
b10 P
b10 C
1(
#862
0(
#864
b11 C
b111 R
b0 P
1(
#866
0(
#868
1$
b100 C
1(
#870
0(
#872
b101 C
1(
#874
0(
#876
b10 =
b0 C
1(
#878
0(
#880
b1 C
b10001 A
1!
1>
b100010010101111010000000 @
1(
#882
0(
#884
b1 P
b10 C
b100010010101111011000000 @
1(
#886
0(
#888
b11 C
b11 P
1(
#890
0(
#892
b100 C
1(
#894
0(
#896
b101 C
1(
#898
0(
#900
b1 =
b0 C
1(
#902
0(
#904
b1 C
0!
0>
1(
#906
0(
#908
b10 P
b10 C
1(
#910
0(
#912
b11 C
b110 R
b0 P
1(
#914
0(
#916
0$
b100 C
1(
#918
0(
#920
b101 C
1(
#922
0(
#924
b10 =
b0 C
1(
#926
0(
#928
b1 C
b10010 A
1!
1>
b100010010101111010000000 @
1(
#930
0(
#932
b1 P
b10 C
1(
#934
0(
#936
b11 C
b11 P
1(
#938
0(
#940
b100 C
1(
#942
0(
#944
b101 C
1(
#946
0(
#948
b1 =
b0 C
1(
#950
0(
#952
b1 C
0!
0>
1#
1(
#954
0(
#956
b10 P
b10 C
1(
#958
0(
#960
b11 C
b101 R
b0 P
1(
#962
0(
#964
b100 C
1(
#966
0(
#968
b101 C
1(
#970
0(
#972
b10 =
b0 C
1(
#974
0(
#976
b1 C
b10011 A
1!
1>
1(
#978
0(
#980
b1 P
b10 C
1(
#982
0(
#984
b11 C
b101010011010100100000 &
b101010011010100100000 O
b11 P
1(
#986
0(
#988
b100 C
1(
#990
0(
#992
b101 C
1(
#994
0(
#996
b1 =
b0 C
1(
#998
0(
#1000
b1 C
0!
0>
0#
1(
#1002
0(
#1004
b10 P
b10 C
1(
#1006
0(
#1008
b11 C
b100 R
b0 P
1(
#1010
0(
#1012
b100 C
1(
#1014
0(
#1016
b101 C
1(
#1018
0(
#1020
b10 =
b0 C
1(
#1022
0(
#1024
b1 C
b10100 A
1!
1>
1(
#1026
0(
#1028
b1 P
b10 C
1(
#1030
0(
#1032
b11 C
b11 P
1(
#1034
0(
#1036
b100 C
1(
#1038
0(
#1040
b101 C
1(
#1042
0(
#1044
b1 =
b0 C
1(
#1046
0(
#1048
b1 C
0!
0>
1(
#1050
0(
#1052
b10 P
b10 C
1(
#1054
0(
#1056
b11 C
b11 R
b0 P
1(
#1058
0(
#1060
b100 C
1(
#1062
0(
#1064
b101 C
1(
#1066
0(
#1068
b10 =
b0 C
1(
#1070
0(
#1072
b1 C
b10101 A
1!
1>
1(
#1074
0(
#1076
b1 P
b10 C
1(
#1078
0(
#1080
b11 C
b11 P
1(
#1082
0(
#1084
b100 C
1(
#1086
0(
#1088
b101 C
1(
#1090
0(
#1092
b1 =
b0 C
1(
#1094
0(
#1096
b1 C
0!
0>
1#
1(
#1098
0(
#1100
b10 P
b10 C
1(
#1102
0(
#1104
b11 C
b10 R
b0 P
1(
#1106
0(
#1108
b100 C
1(
#1110
0(
#1112
b101 C
1(
#1114
0(
#1116
b10 =
b0 C
1(
#1118
0(
#1120
b1 C
b10110 A
1!
1>
1(
#1122
0(
#1124
b1 P
b10 C
1(
#1126
0(
#1128
b11 C
b101010011010100100100 &
b101010011010100100100 O
b11 P
1(
#1130
0(
#1132
b100 C
1(
#1134
0(
#1136
b101 C
1(
#1138
0(
#1140
b1 =
b0 C
1(
#1142
0(
#1144
b1 C
0!
0>
0#
1(
#1146
0(
#1148
b10 P
b10 C
1(
#1150
0(
#1152
b11 C
b1 R
b0 P
1(
#1154
0(
#1156
b100 C
1(
#1158
0(
#1160
b101 C
1(
#1162
0(
#1164
b10 =
b0 C
1(
#1166
0(
#1168
b1 C
b10111 A
1!
1>
1(
#1170
0(
#1172
b1 P
b10 C
1(
#1174
0(
#1176
b11 C
b11 P
1(
#1178
0(
#1180
b100 C
1(
#1182
0(
#1184
b101 C
1(
#1186
0(
#1188
b1 =
b0 C
1(
#1190
0(
#1192
b1 C
0!
0>
1(
#1194
0(
#1196
b10 P
b10 C
1(
#1198
0(
#1200
b11 C
b0 R
b0 P
1(
#1202
0(
#1204
1$
b100 C
1(
#1206
0(
#1208
b101 C
1(
#1210
0(
#1212
b10 =
b0 C
1(
#1214
0(
#1216
b1 C
b11000 A
1!
1>
b100010010101111010000001 @
1(
#1218
0(
#1220
b1 P
b10 C
1(
#1222
0(
#1224
b11 C
b11 P
1(
#1226
0(
#1228
b100 C
1(
#1230
0(
#1232
b101 C
1(
#1234
0(
#1236
1%
b0 =
b0 C
1(
#1238
0(
#1240
b100010010101111010000001 '
b100010010101111010000001 <
b0 A
0!
0>
1(
#1242
0(
#1244
b10 P
1(
#1246
0(
#1248
1"
0J
b111111 R
b10 Q
b0 P
1(
#1250
0(
#1252
0"
b0 Q
b10111 R
1(
