modules/uart/source/uart_rx.v
module uart_rx # (
  parameter p_preescaler = 8, /* clock preescaler to set baudrate */
  parameter p_data_buffer = 16 /* number of bytes to receive */
)(
  input clk, 
  input rst, /* synchronous reset */
  (* MARK_DEBUG = "TRUE" *) input i_rx, /* uart reception line */
  output reg [8*p_data_buffer-1:0] orp_data, /* data received */
  (* MARK_DEBUG = "TRUE" *) output reg or_dv /* output data valid */
);

localparam lpw_preescaler_counter = $clog2(p_preescaler);
localparam lp_max_data_bit = (p_data_buffer*8) - 1;

reg [lpw_preescaler_counter-1:0] rp_preescaler_counter;
reg r_uart_tick;

/* Baudrate preescaler */
always@(posedge clk) begin
  if(rst) begin
    rp_preescaler_counter <= 0;
    r_uart_tick <= 1'b0;
  end
  else begin
    if(rp_preescaler_counter < (p_preescaler-1)) begin
      rp_preescaler_counter <= rp_preescaler_counter + 1;
      r_uart_tick <= 1'b0;
    end
    else begin
      rp_preescaler_counter <= 0;
      r_uart_tick <= 1'b1;
    end
  end
end

localparam st_idle = 3'd0;
localparam st_start = 3'd1;
localparam st_receive = 3'd2;
localparam st_stop = 3'd3;
localparam st_next_byte = 3'd4;
localparam st_end = 3'd5;

(* MARK_DEBUG = "TRUE" *) reg [2:0] r3_state; /* FSM state */
reg [8*p_data_buffer-1:0] rp_data; /* complete data */
reg [7:0] r8_byte_rcv; /* Actual byte sending */

reg [15:0] r16_data_index; /* byte data index */
reg [2:0] r3_nBit; /* bit counter inside a bytes */

always@(posedge clk) begin
  if(rst) begin
    r3_state <= st_idle;
    r3_nBit <= 3'd0;
    or_dv <= 1'b0;
  end
  else begin
    case(r3_state)
      st_idle: begin // start bit
        
        if(i_rx == 1'b0) r3_state <= st_start;
        else r3_state <= st_idle;

        r16_data_index <= lp_max_data_bit;
        r3_nBit <= 0;
        or_dv <= 1'b0;
      end
      st_start: begin 
        
        if(r_uart_tick) r3_state <= st_receive;
        else r3_state <= st_start;

      end
      st_receive: begin
        
        if(r_uart_tick && r3_nBit == 7) r3_state <= st_stop;
        else r3_state <= st_receive;

        r8_byte_rcv[r3_nBit] <= i_rx;
        r3_nBit <= (r_uart_tick) ? r3_nBit + 1 : r3_nBit; // Bit counter

      end
      st_stop: begin
        
        if(r_uart_tick && r16_data_index == 7) r3_state <= st_end;
        else if (r_uart_tick && r16_data_index > 7) r3_state <= st_next_byte;
        else r3_state <= st_stop;

        r16_data_index <= (r_uart_tick) ? r16_data_index - 8 : r16_data_index; // Byte counter
        rp_data[r16_data_index -: 8] <= r8_byte_rcv;

      end
      st_next_byte: begin
        
        if(i_rx == 1'b0) r3_state <= st_start;
        else r3_state <= st_next_byte;

      end
      st_end: begin

        orp_data <= rp_data;
        or_dv <= 1'b1;

        r3_state <= st_idle;

      end
    endcase
  end
end


endmodule

modules/uart/source/uart_tx.v
module uart_tx # (
  parameter p_preescaler = 8, /* clock preescaler to set baudrate (it should be more than 0) */
  parameter p_data_buffer = 16 /* number of bytes to send */
)(
  input clk, 
  input rst, /* synchronous reset */
  input [8*p_data_buffer-1:0] ip_data, /* data to send */
  input i_dv, /* input data valid */
  output o_ready, /* module ready to accept new data */
  output o_tx /* uart transmission line */
);

localparam lpw_preescaler_counter = $clog2(p_preescaler);
localparam lp_max_data_bit = (p_data_buffer*8) - 1;

reg [lpw_preescaler_counter-1:0] rp_preescaler_counter;
reg r_uart_tick;

localparam st_idle = 3'd0;
localparam st_start = 3'd1;
localparam st_transmit = 3'd2;
localparam st_stop = 3'd3;

reg [2:0] r3_state; /* FSM state */
reg [8*p_data_buffer-1:0] rp_data; /* complete data */
reg [7:0] r8_byte_send; /* Actual byte sending */

reg [15:0] r16_data_index; /* byte data index */
reg [2:0] r3_nBit; /* bit counter inside a bytes */

/* Baudrate preescaler */
always@(posedge clk) begin
  if(rst) begin
    rp_preescaler_counter <= 0;
    r_uart_tick <= 1'b0;
  end
  else begin
    if(rp_preescaler_counter < (p_preescaler-1)) begin
      rp_preescaler_counter <= rp_preescaler_counter + 1;
      r_uart_tick <= 1'b0;
    end
    else begin
      rp_preescaler_counter <= 0;
      r_uart_tick <= 1'b1;
    end
  end
end


/*

Uart spec:

![image](uart_spec.png)

*/

always@(posedge clk) begin
  if(rst) begin
    r3_state <= st_idle;
    r3_nBit <= 3'd0;
  end
  else begin
    case(r3_state)
      st_idle: begin // Register inputs
        
        if(i_dv) r3_state <= st_start;
        else r3_state <= st_idle;
            
        rp_data <= ip_data;   
        r16_data_index <= lp_max_data_bit; // Init data index to max bit (send first MSB byte)
        r3_nBit <= 3'd0; // Init byte index to bit 0 (send first bit 0 of byte high)

      end
      st_start: begin // Start bit

        if(r_uart_tick) r3_state <= st_transmit;
        else r3_state <= st_start;
        
        r8_byte_send <= rp_data[r16_data_index -: 8]; // Get byte

      end
      st_transmit: begin // Transmit a byte

        if(r_uart_tick && r3_nBit == 7) r3_state <= st_stop; // 8 bits send
        else r3_state <= st_transmit;

        r3_nBit <= (r_uart_tick) ? r3_nBit + 1 : r3_nBit; // Bit counter

      end
      st_stop: begin // Stop bit (1 stop bit)

      if(r_uart_tick && r16_data_index == 7) r3_state <= st_idle; // Last byte sended
      else if(r_uart_tick && r16_data_index > 7) r3_state <= st_start; // Continue with next byte
      else r3_state <= st_stop; 

      r16_data_index <= (r_uart_tick) ? r16_data_index - 8 : r16_data_index; // Byte counter

      end
    endcase
  end
end

/* TX Output */
assign o_tx = (r3_state == st_transmit) ? r8_byte_send[r3_nBit] : ((r3_state == st_start) ? 1'b0 : 1'b1);

/* Ready */
assign o_ready = (r3_state == st_idle) ? 1'b1 : 1'b0;

endmodule

modules/uart/test/uart_tb.v
/**** Global timescale ****/
`timescale 10ns/10ns
`define clkcycle 4

/**** Global definitions ****/
`define _1us 100
`define _10us 1000
`define _100us 10000
`define _1ms 100000
`define _10ms 1000000
`define _100ms 10000000
`define _100ns 10
`define _40ns 4
`define _30ns 3

`define max_test_cases 4

module uart_tb();

  /**** Fixed test signals ****/
  integer fd;
  integer error_counter = 0;
  integer test_count = 0;
  integer i;
  integer flag = 0;
  integer verbose = 0;

  /**** Test signals ****/
  reg clk25;
  reg resetn;

  wire w_tx;
  wire w_new_data_rcv;
  wire [31:0] w32_rcv_data;

  reg r_new_data_send;
  reg [31:0] r31_send_data;

  /**** Clock generation ****/
  initial begin
    clk25 = 1'b0;
    #(`clkcycle/2);
    forever
    #(`clkcycle/2) clk25 = ~clk25;
  end

  /**** Test modules instantiation ****/
  uart_tx # (
    .p_preescaler(4), /* clock preescaler to set baudrate */
    .p_data_buffer(4) /* number of bytes to send */
  ) uart_tx (
    .clk(clk25), 
    .rst(!resetn), /* synchronous reset */
    .ip_data(r31_send_data), /* data to send */
    .i_dv(r_new_data_send), /* input data valid */
    .o_ready(), /* module ready to accept new data */
    .o_tx(w_tx) /* uart transmission line */
  );

  uart_rx #(
	  .p_preescaler(4), /* Prescaler for baudrate */
	  .p_data_buffer(4) /* Indicates number of bytes to receive */
  ) uart_rx (
	  .clk(clk25), /* Input clock */
	  .rst(!resetn), /* Input reset */
	  .i_rx(w_tx),	/* Input rx pin */
    .orp_data(w32_rcv_data),	/* Parallel data port */
    .or_dv(w_new_data_rcv) /* New data available in data port */ 
	);

  /**** Test flow ****/
  initial begin

    $dumpfile ("uart_tb.vcd"); // Change filename as appropriate. 
    $dumpvars();

    $display("[INFO] >> Setting initial conditions.");
    
    /*** Reset management ***/
    reset_task();

    /*** Init test flow ***/
    $display("[INFO] >> Test init");
    r_new_data_send <= 1'b0;
   
    /*** Test cases ***/
    repeat(10) begin
      packet_send();
      #(`_10us);
    end

    #(`_1us);
    $finish();

  end

  task packet_send;
  begin

    r_new_data_send <= 1'b1;
    r31_send_data <= $urandom();

    #(`clkcycle);
    r_new_data_send <= 1'b0;

    fork
      begin: f_timeout
        #(`_1ms);
        $error("[ERROR]: No data received");
        disable f_ok;
      end
      begin: f_ok
        @(posedge w_new_data_rcv);
        if(w32_rcv_data != r31_send_data) $error("[ERROR]: Sended data %h - Received data %h", r31_send_data, w32_rcv_data);
        else $display("[OK]: Sended data %h - Received data %h", r31_send_data, w32_rcv_data);

        disable f_timeout;
      end
    join

  end
  endtask

  task reset_task;
  begin
    $info("Resetting module.");
    resetn <= 0;

    $info("Release Reset");
    #(20*`clkcycle);
    resetn <= 1;

  end
  endtask

endmodule

modules/uart/test/uart_tb.vcd
$date
	Thu May 01 17:28:23 2025
$end
$version
	Icarus Verilog
$end
$timescale
	10ns
$end
$scope module uart_tb $end
$var wire 1 ! w_tx $end
$var wire 1 " w_new_data_rcv $end
$var wire 32 # w32_rcv_data [31:0] $end
$var reg 1 $ clk25 $end
$var reg 32 % r31_send_data [31:0] $end
$var reg 1 & r_new_data_send $end
$var reg 1 ' resetn $end
$var integer 32 ( error_counter [31:0] $end
$var integer 32 ) flag [31:0] $end
$var integer 32 * test_count [31:0] $end
$var integer 32 + verbose [31:0] $end
$scope module uart_rx $end
$var wire 1 $ clk $end
$var wire 1 , rst $end
$var wire 1 ! i_rx $end
$var parameter 65 - lp_max_data_bit $end
$var parameter 32 . lpw_preescaler_counter $end
$var parameter 32 / p_data_buffer $end
$var parameter 32 0 p_preescaler $end
$var parameter 3 1 st_end $end
$var parameter 3 2 st_idle $end
$var parameter 3 3 st_next_byte $end
$var parameter 3 4 st_receive $end
$var parameter 3 5 st_start $end
$var parameter 3 6 st_stop $end
$var reg 1 " or_dv $end
$var reg 32 7 orp_data [31:0] $end
$var reg 16 8 r16_data_index [15:0] $end
$var reg 3 9 r3_nBit [2:0] $end
$var reg 3 : r3_state [2:0] $end
$var reg 8 ; r8_byte_rcv [7:0] $end
$var reg 1 < r_uart_tick $end
$var reg 32 = rp_data [31:0] $end
$var reg 2 > rp_preescaler_counter [1:0] $end
$upscope $end
$scope module uart_tx $end
$var wire 1 $ clk $end
$var wire 1 & i_dv $end
$var wire 32 ? ip_data [31:0] $end
$var wire 1 @ rst $end
$var wire 1 ! o_tx $end
$var wire 1 A o_ready $end
$var parameter 65 B lp_max_data_bit $end
$var parameter 32 C lpw_preescaler_counter $end
$var parameter 32 D p_data_buffer $end
$var parameter 32 E p_preescaler $end
$var parameter 3 F st_idle $end
$var parameter 3 G st_start $end
$var parameter 3 H st_stop $end
$var parameter 3 I st_transmit $end
$var reg 16 J r16_data_index [15:0] $end
$var reg 3 K r3_nBit [2:0] $end
$var reg 3 L r3_state [2:0] $end
$var reg 8 M r8_byte_send [7:0] $end
$var reg 1 N r_uart_tick $end
$var reg 32 O rp_data [31:0] $end
$var reg 2 P rp_preescaler_counter [1:0] $end
$upscope $end
$scope task packet_send $end
$scope begin f_ok $end
$upscope $end
$scope begin f_timeout $end
$upscope $end
$upscope $end
$scope task reset_task $end
$upscope $end
$upscope $end
$enddefinitions $end
$comment Show the parameter values. $end
$dumpall
b10 I
b11 H
b1 G
b0 F
b100 E
b100 D
b10 C
b11111 B
b11 6
b1 5
b10 4
b100 3
b0 2
b101 1
b100 0
b100 /
b10 .
b11111 -
$end
#0
$dumpvars
bx P
bx O
xN
bx M
bx L
bx K
bx J
xA
1@
bx ?
bx >
bx =
x<
bx ;
bx :
bx 9
bx 8
bx 7
1,
b0 +
b0 *
b0 )
b0 (
0'
x&
bx %
0$
bx #
x"
x!
$end
#4
1!
1A
0N
b0 P
b0 K
b0 L
0<
b0 >
0"
b0 9
b0 :
1$
#6
0$
#8
1$
#10
0$
#12
1$
#14
0$
#16
1$
#18
0$
#20
1$
#22
0$
#24
1$
#26
0$
#28
1$
#30
0$
#32
1$
#34
0$
#36
1$
#38
0$
#40
1$
#42
0$
#44
1$
#46
0$
#48
1$
#50
0$
#52
1$
#54
0$
#56
1$
#58
0$
#60
1$
#62
0$
#64
1$
#66
0$
#68
1$
#70
0$
#72
1$
#74
0$
#76
1$
#78
0$
#80
b10010010000101010011010100100100 %
b10010010000101010011010100100100 ?
1&
0@
0,
1'
1$
#82
0$
#84
0!
0A
b1 P
b11111 J
b10010010000101010011010100100100 O
b1 L
b1 >
b11111 8
0&
1$
#86
0$
#88
b1 :
b10 >
b10010010 M
b10 P
1$
#90
0$
#92
b11 P
b11 >
1$
#94
0$
#96
1<
b0 >
1N
b0 P
1$
#98
0$
#100
0N
b1 P
b10 L
0<
b1 >
b10 :
1$
#102
0$
#104
bx0 ;
b10 >
b10 P
1$
#106
0$
#108
b11 P
b11 >
1$
#110
0$
#112
1<
b0 >
1N
b0 P
1$
#114
0$
#116
1!
0N
b1 P
b1 K
0<
b1 >
b1 9
1$
#118
0$
#120
bx10 ;
b10 >
b10 P
1$
#122
0$
#124
b11 P
b11 >
1$
#126
0$
#128
1<
b0 >
1N
b0 P
1$
#130
0$
#132
0!
0N
b1 P
b10 K
0<
b1 >
b10 9
1$
#134
0$
#136
bx010 ;
b10 >
b10 P
1$
#138
0$
#140
b11 P
b11 >
1$
#142
0$
#144
1<
b0 >
1N
b0 P
1$
#146
0$
#148
0N
b1 P
b11 K
0<
b1 >
b11 9
1$
#150
0$
#152
bx0010 ;
b10 >
b10 P
1$
#154
0$
#156
b11 P
b11 >
1$
#158
0$
#160
1<
b0 >
1N
b0 P
1$
#162
0$
#164
1!
0N
b1 P
b100 K
0<
b1 >
b100 9
1$
#166
0$
#168
bx10010 ;
b10 >
b10 P
1$
#170
0$
#172
b11 P
b11 >
1$
#174
0$
#176
1<
b0 >
1N
b0 P
1$
#178
0$
#180
0!
0N
b1 P
b101 K
0<
b1 >
b101 9
1$
#182
0$
#184
bx010010 ;
b10 >
b10 P
1$
#186
0$
#188
b11 P
b11 >
1$
#190
0$
#192
1<
b0 >
1N
b0 P
1$
#194
0$
#196
0N
b1 P
b110 K
0<
b1 >
b110 9
1$
#198
0$
#200
bx0010010 ;
b10 >
b10 P
1$
#202
0$
#204
b11 P
b11 >
1$
#206
0$
#208
1<
b0 >
1N
b0 P
1$
#210
0$
#212
1!
0N
b1 P
b111 K
0<
b1 >
b111 9
1$
#214
0$
#216
b10010010 ;
b10 >
b10 P
1$
#218
0$
#220
b11 P
b11 >
1$
#222
0$
#224
1<
b0 >
1N
b0 P
1$
#226
0$
#228
0N
b1 P
b0 K
b11 L
0<
b1 >
b0 9
b11 :
1$
#230
0$
#232
b10010010xxxxxxxxxxxxxxxxxxxxxxxx =
b10 >
b10 P
1$
#234
0$
#236
b11 P
b11 >
1$
#238
0$
#240
1<
b0 >
1N
b0 P
1$
#242
0$
#244
0!
0N
b1 P
b10111 J
b1 L
0<
b1 >
b10111 8
b100 :
1$
#246
0$
#248
b1 :
b10 >
b10101 M
b10 P
1$
#250
0$
#252
b11 P
b11 >
1$
#254
0$
#256
1<
b0 >
1N
b0 P
1$
#258
0$
#260
1!
0N
b1 P
b10 L
0<
b1 >
b10 :
1$
#262
0$
#264
b10010011 ;
b10 >
b10 P
1$
#266
0$
#268
b11 P
b11 >
1$
#270
0$
#272
1<
b0 >
1N
b0 P
1$
#274
0$
#276
0!
0N
b1 P
b1 K
0<
b1 >
b1 9
1$
#278
0$
#280
b10010001 ;
b10 >
b10 P
1$
#282
0$
#284
b11 P
b11 >
1$
#286
0$
#288
1<
b0 >
1N
b0 P
1$
#290
0$
#292
1!
0N
b1 P
b10 K
0<
b1 >
b10 9
1$
#294
0$
#296
b10010101 ;
b10 >
b10 P
1$
#298
0$
#300
b11 P
b11 >
1$
#302
0$
#304
1<
b0 >
1N
b0 P
1$
#306
0$
#308
0!
0N
b1 P
b11 K
0<
b1 >
b11 9
1$
#310
0$
#312
b10 >
b10 P
1$
#314
0$
#316
b11 P
b11 >
1$
#318
0$
#320
1<
b0 >
1N
b0 P
1$
#322
0$
#324
1!
0N
b1 P
b100 K
0<
b1 >
b100 9
1$
#326
0$
#328
b10 >
b10 P
1$
#330
0$
#332
b11 P
b11 >
1$
#334
0$
#336
1<
b0 >
1N
b0 P
1$
#338
0$
#340
0!
0N
b1 P
b101 K
0<
b1 >
b101 9
1$
#342
0$
#344
b10 >
b10 P
1$
#346
0$
#348
b11 P
b11 >
1$
#350
0$
#352
1<
b0 >
1N
b0 P
1$
#354
0$
#356
0N
b1 P
b110 K
0<
b1 >
b110 9
1$
#358
0$
#360
b10 >
b10 P
1$
#362
0$
#364
b11 P
b11 >
1$
#366
0$
#368
1<
b0 >
1N
b0 P
1$
#370
0$
#372
0N
b1 P
b111 K
0<
b1 >
b111 9
1$
#374
0$
#376
b10101 ;
b10 >
b10 P
1$
#378
0$
#380
b11 P
b11 >
1$
#382
0$
#384
1<
b0 >
1N
b0 P
1$
#386
0$
#388
1!
0N
b1 P
b0 K
b11 L
0<
b1 >
b0 9
b11 :
1$
#390
0$
#392
b1001001000010101xxxxxxxxxxxxxxxx =
b10 >
b10 P
1$
#394
0$
#396
b11 P
b11 >
1$
#398
0$
#400
1<
b0 >
1N
b0 P
1$
#402
0$
#404
0!
0N
b1 P
b1111 J
b1 L
0<
b1 >
b1111 8
b100 :
1$
#406
0$
#408
b1 :
b10 >
b110101 M
b10 P
1$
#410
0$
#412
b11 P
b11 >
1$
#414
0$
#416
1<
b0 >
1N
b0 P
1$
#418
0$
#420
1!
0N
b1 P
b10 L
0<
b1 >
b10 :
1$
#422
0$
#424
b10 >
b10 P
1$
#426
0$
#428
b11 P
b11 >
1$
#430
0$
#432
1<
b0 >
1N
b0 P
1$
#434
0$
#436
0!
0N
b1 P
b1 K
0<
b1 >
b1 9
1$
#438
0$
#440
b10 >
b10 P
1$
#442
0$
#444
b11 P
b11 >
1$
#446
0$
#448
1<
b0 >
1N
b0 P
1$
#450
0$
#452
1!
0N
b1 P
b10 K
0<
b1 >
b10 9
1$
#454
0$
#456
b10 >
b10 P
1$
#458
0$
#460
b11 P
b11 >
1$
#462
0$
#464
1<
b0 >
1N
b0 P
1$
#466
0$
#468
0!
0N
b1 P
b11 K
0<
b1 >
b11 9
1$
#470
0$
#472
b10 >
b10 P
1$
#474
0$
#476
b11 P
b11 >
1$
#478
0$
#480
1<
b0 >
1N
b0 P
1$
#482
0$
#484
1!
0N
b1 P
b100 K
0<
b1 >
b100 9
1$
#486
0$
#488
b10 >
b10 P
1$
#490
0$
#492
b11 P
b11 >
1$
#494
0$
#496
1<
b0 >
1N
b0 P
1$
#498
0$
#500
0N
b1 P
b101 K
0<
b1 >
b101 9
1$
#502
0$
#504
b110101 ;
b10 >
b10 P
1$
#506
0$
#508
b11 P
b11 >
1$
#510
0$
#512
1<
b0 >
1N
b0 P
1$
#514
0$
#516
0!
0N
b1 P
b110 K
0<
b1 >
b110 9
1$
#518
0$
#520
b10 >
b10 P
1$
#522
0$
#524
b11 P
b11 >
1$
#526
0$
#528
1<
b0 >
1N
b0 P
1$
#530
0$
#532
0N
b1 P
b111 K
0<
b1 >
b111 9
1$
#534
0$
#536
b10 >
b10 P
1$
#538
0$
#540
b11 P
b11 >
1$
#542
0$
#544
1<
b0 >
1N
b0 P
1$
#546
0$
#548
1!
0N
b1 P
b0 K
b11 L
0<
b1 >
b0 9
b11 :
1$
#550
0$
#552
b100100100001010100110101xxxxxxxx =
b10 >
b10 P
1$
#554
0$
#556
b11 P
b11 >
1$
#558
0$
#560
1<
b0 >
1N
b0 P
1$
#562
0$
#564
0!
0N
b1 P
b111 J
b1 L
0<
b1 >
b111 8
b100 :
1$
#566
0$
#568
b1 :
b10 >
b100100 M
b10 P
1$
#570
0$
#572
b11 P
b11 >
1$
#574
0$
#576
1<
b0 >
1N
b0 P
1$
#578
0$
#580
0N
b1 P
b10 L
0<
b1 >
b10 :
1$
#582
0$
#584
b110100 ;
b10 >
b10 P
1$
#586
0$
#588
b11 P
b11 >
1$
#590
0$
#592
1<
b0 >
1N
b0 P
1$
#594
0$
#596
0N
b1 P
b1 K
0<
b1 >
b1 9
1$
#598
0$
#600
b10 >
b10 P
1$
#602
0$
#604
b11 P
b11 >
1$
#606
0$
#608
1<
b0 >
1N
b0 P
1$
#610
0$
#612
1!
0N
b1 P
b10 K
0<
b1 >
b10 9
1$
#614
0$
#616
b10 >
b10 P
1$
#618
0$
#620
b11 P
b11 >
1$
#622
0$
#624
1<
b0 >
1N
b0 P
1$
#626
0$
#628
0!
0N
b1 P
b11 K
0<
b1 >
b11 9
1$
#630
0$
#632
b10 >
b10 P
1$
#634
0$
#636
b11 P
b11 >
1$
#638
0$
#640
1<
b0 >
1N
b0 P
1$
#642
0$
#644
0N
b1 P
b100 K
0<
b1 >
b100 9
1$
#646
0$
#648
b100100 ;
b10 >
b10 P
1$
#650
0$
#652
b11 P
b11 >
1$
#654
0$
#656
1<
b0 >
1N
b0 P
1$
#658
0$
#660
1!
0N
b1 P
b101 K
0<
b1 >
b101 9
1$
#662
0$
#664
b10 >
b10 P
1$
#666
0$
#668
b11 P
b11 >
1$
#670
0$
#672
1<
b0 >
1N
b0 P
1$
#674
0$
#676
0!
0N
b1 P
b110 K
0<
b1 >
b110 9
1$
#678
0$
#680
b10 >
b10 P
1$
#682
0$
#684
b11 P
b11 >
1$
#686
0$
#688
1<
b0 >
1N
b0 P
1$
#690
0$
#692
0N
b1 P
b111 K
0<
b1 >
b111 9
1$
#694
0$
#696
b10 >
b10 P
1$
#698
0$
#700
b11 P
b11 >
1$
#702
0$
#704
1<
b0 >
1N
b0 P
1$
#706
0$
#708
1!
0N
b1 P
b0 K
b11 L
0<
b1 >
b0 9
b11 :
1$
#710
0$
#712
b10010010000101010011010100100100 =
b10 >
b10 P
1$
#714
0$
#716
b11 P
b11 >
1$
#718
0$
#720
1<
b0 >
1N
b0 P
1$
#722
0$
#724
1A
0N
b1 P
b1111111111111111 J
b0 L
0<
b1 >
b1111111111111111 8
b101 :
1$
#726
0$
#728
b0 :
1"
b10010010000101010011010100100100 #
b10010010000101010011010100100100 7
b10 >
b11111 J
b10 P
1$
#730
0$
#732
b11 P
b11 >
0"
b11111 8
1$
#734
0$
#736
1<
b0 >
1N
b0 P
1$
#738
0$
#740
0N
b1 P
0<
b1 >
1$
#742
0$
#744
b10 >
b10 P
1$
#746
0$
#748
b11 P
b11 >
1$
#750
0$
#752
1<
b0 >
1N
b0 P
1$
#754
0$
#756
0N
b1 P
0<
b1 >
1$
#758
0$
#760
b10 >
b10 P
1$
#762
0$
#764
b11 P
b11 >
1$
#766
0$
#768
1<
b0 >
1N
b0 P
1$
#770
0$
#772
0N
b1 P
0<
b1 >
1$
#774
0$
#776
b10 >
b10 P
1$
#778
0$
#780
b11 P
b11 >
1$
#782
0$
#784
1<
b0 >
1N
b0 P
1$
#786
0$
#788
0N
b1 P
0<
b1 >
1$
#790
0$
#792
b10 >
b10 P
1$
#794
0$
#796
b11 P
b11 >
1$
#798
0$
#800
1<
b0 >
1N
b0 P
1$
#802
0$
#804
0N
b1 P
0<
b1 >
1$
#806
0$
#808
b10 >
b10 P
1$
#810
0$
#812
b11 P
b11 >
1$
#814
0$
#816
1<
b0 >
1N
b0 P
1$
#818
0$
#820
0N
b1 P
0<
b1 >
1$
#822
0$
#824
b10 >
b10 P
1$
#826
0$
#828
b11 P
b11 >
1$
#830
0$
#832
1<
b0 >
1N
b0 P
1$
#834
0$
#836
0N
b1 P
0<
b1 >
1$
#838
0$
#840
b10 >
b10 P
1$
#842
0$
#844
b11 P
b11 >
1$
#846
0$
#848
1<
b0 >
1N
b0 P
1$
#850
0$
#852
0N
b1 P
0<
b1 >
1$
#854
0$
#856
b10 >
b10 P
1$
#858
0$
#860
b11 P
b11 >
1$
#862
0$
#864
1<
b0 >
1N
b0 P
1$
#866
0$
#868
0N
b1 P
0<
b1 >
1$
#870
0$
#872
b10 >
b10 P
1$
#874
0$
#876
b11 P
b11 >
1$
#878
0$
#880
1<
b0 >
1N
b0 P
1$
#882
0$
#884
0N
b1 P
0<
b1 >
1$
#886
0$
#888
b10 >
b10 P
1$
#890
0$
#892
b11 P
b11 >
1$
#894
0$
#896
1<
b0 >
1N
b0 P
1$
#898
0$
#900
0N
b1 P
0<
b1 >
1$
#902
0$
#904
b10 >
b10 P
1$
#906
0$
#908
b11 P
b11 >
1$
#910
0$
#912
1<
b0 >
1N
b0 P
1$
#914
0$
#916
0N
b1 P
0<
b1 >
1$
#918
0$
#920
b10 >
b10 P
1$
#922
0$
#924
b11 P
b11 >
1$
#926
0$
#928
1<
b0 >
1N
b0 P
1$
#930
0$
#932
0N
b1 P
0<
b1 >
1$
#934
0$
#936
b10 >
b10 P
1$
#938
0$
#940
b11 P
b11 >
1$
#942
0$
#944
1<
b0 >
1N
b0 P
1$
#946
0$
#948
0N
b1 P
0<
b1 >
1$
#950
0$
#952
b10 >
b10 P
1$
#954
0$
#956
b11 P
b11 >
1$
#958
0$
#960
1<
b0 >
1N
b0 P
1$
#962
0$
#964
0N
b1 P
0<
b1 >
1$
#966
0$
#968
b10 >
b10 P
1$
#970
0$
#972
b11 P
b11 >
1$
#974
0$
#976
1<
b0 >
1N
b0 P
1$
#978
0$
#980
0N
b1 P
0<
b1 >
1$
#982
0$
#984
b10 >
b10 P
1$
#986
0$
#988
b11 P
b11 >
1$
#990
0$
#992
1<
b0 >
1N
b0 P
1$
#994
0$
#996
0N
b1 P
0<
b1 >
1$
#998
0$
#1000
b10 >
b10 P
1$
#1002
0$
#1004
b11 P
b11 >
1$
#1006
0$
#1008
1<
b0 >
1N
b0 P
1$
#1010
0$
#1012
0N
b1 P
0<
b1 >
1$
#1014
0$
#1016
b10 >
b10 P
1$
#1018
0$
#1020
b11 P
b11 >
1$
#1022
0$
#1024
1<
b0 >
1N
b0 P
1$
#1026
0$
#1028
0N
b1 P
0<
b1 >
1$
#1030
0$
#1032
b10 >
b10 P
1$
#1034
0$
#1036
b11 P
b11 >
1$
#1038
0$
#1040
1<
b0 >
1N
b0 P
1$
#1042
0$
#1044
0N
b1 P
0<
b1 >
1$
#1046
0$
#1048
b10 >
b10 P
1$
#1050
0$
#1052
b11 P
b11 >
1$
#1054
0$
#1056
1<
b0 >
1N
b0 P
1$
#1058
0$
#1060
0N
b1 P
0<
b1 >
1$
#1062
0$
#1064
b10 >
b10 P
1$
#1066
0$
#1068
b11 P
b11 >
1$
#1070
0$
#1072
1<
b0 >
1N
b0 P
1$
#1074
0$
#1076
0N
b1 P
0<
b1 >
1$
#1078
0$
#1080
b10 >
b10 P
1$
#1082
0$
#1084
b11 P
b11 >
1$
#1086
0$
#1088
1<
b0 >
1N
b0 P
1$
#1090
0$
#1092
0N
b1 P
0<
b1 >
1$
#1094
0$
#1096
b10 >
b10 P
1$
#1098
0$
#1100
b11 P
b11 >
1$
#1102
0$
#1104
1<
b0 >
1N
b0 P
1$
#1106
0$
#1108
0N
b1 P
0<
b1 >
1$
#1110
0$
#1112
b10 >
b10 P
1$
#1114
0$
#1116
b11 P
b11 >
1$
#1118
0$
#1120
1<
b0 >
1N
b0 P
1$
#1122
0$
#1124
0N
b1 P
0<
b1 >
1$
#1126
0$
#1128
b10 >
b10 P
1$
#1130
0$
#1132
b11 P
b11 >
1$
#1134
0$
#1136
1<
b0 >
1N
b0 P
1$
#1138
0$
#1140
0N
b1 P
0<
b1 >
1$
#1142
0$
#1144
b10 >
b10 P
1$
#1146
0$
#1148
b11 P
b11 >
1$
#1150
0$
#1152
1<
b0 >
1N
b0 P
1$
#1154
0$
#1156
0N
b1 P
0<
b1 >
1$
#1158
0$
#1160
b10 >
b10 P
1$
#1162
0$
#1164
b11 P
b11 >
1$
#1166
0$
#1168
1<
b0 >
1N
b0 P
1$
#1170
0$
#1172
0N
b1 P
0<
b1 >
1$
#1174
0$
#1176
b10 >
b10 P
1$
#1178
0$
#1180
b11 P
b11 >
1$
#1182
0$
#1184
1<
b0 >
1N
b0 P
1$
#1186
0$
#1188
0N
b1 P
0<
b1 >
1$
#1190
0$
#1192
b10 >
b10 P
1$
#1194
0$
#1196
b11 P
b11 >
1$
#1198
0$
#1200
1<
b0 >
1N
b0 P
1$
#1202
0$
#1204
0N
b1 P
0<
b1 >
1$
#1206
0$
#1208
b10 >
b10 P
1$
#1210
0$
#1212
b11 P
b11 >
1$
#1214
0$
#1216
1<
b0 >
1N
b0 P
1$
#1218
0$
#1220
0N
b1 P
0<
b1 >
1$
#1222
0$
#1224
b10 >
b10 P
1$
#1226
0$
#1228
b11 P
b11 >
1$
#1230
0$
#1232
1<
b0 >
1N
b0 P
1$
#1234
0$
#1236
0N
b1 P
0<
b1 >
1$
#1238
0$
#1240
b10 >
b10 P
1$
#1242
0$
#1244
b11 P
b11 >
1$
#1246
0$
#1248
1<
b0 >
1N
b0 P
1$
#1250
0$
#1252
0N
b1 P
0<
b1 >
1$
#1254
0$
#1256
b10 >
b10 P
1$
#1258
0$
#1260
b11 P
b11 >
1$
#1262
0$
#1264
1<
b0 >
1N
b0 P
1$
#1266
0$
#1268
0N
b1 P
0<
b1 >
1$
#1270
0$
#1272
b10 >
b10 P
1$
#1274
0$
#1276
b11 P
b11 >
1$
#1278
0$
#1280
1<
b0 >
1N
b0 P
1$
#1282
0$
#1284
0N
b1 P
0<
b1 >
1$
#1286
0$
#1288
b10 >
b10 P
1$
#1290
0$
#1292
b11 P
b11 >
1$
#1294
0$
#1296
1<
b0 >
1N
b0 P
1$
#1298
0$
#1300
0N
b1 P
0<
b1 >
1$
#1302
0$
#1304
b10 >
b10 P
1$
#1306
0$
#1308
b11 P
b11 >
1$
#1310
0$
#1312
1<
b0 >
1N
b0 P
1$
#1314
0$
#1316
0N
b1 P
0<
b1 >
1$
#1318
0$
#1320
b10 >
b10 P
1$
#1322
0$
#1324
b11 P
b11 >
1$
#1326
0$
#1328
1<
b0 >
1N
b0 P
1$
#1330
0$
#1332
0N
b1 P
0<
b1 >
1$
#1334
0$
#1336
b10 >
b10 P
1$
#1338
0$
#1340
b11 P
b11 >
1$
#1342
0$
#1344
1<
b0 >
1N
b0 P
1$
#1346
0$
